forloop_modules/__init__.py
forloop_modules/flog.py
forloop_modules/flog_archived.py
forloop_modules/node_detail_form.py
forloop_modules/pipeline_function_handlers.py
forloop_modules/errors/__init__.py
forloop_modules/errors/errors.py
forloop_modules/function_handlers/__init__.py
forloop_modules/function_handlers/api_endpoint_handlers.py
forloop_modules/function_handlers/api_handlers.py
forloop_modules/function_handlers/browser_handlers.py
forloop_modules/function_handlers/cleaning_handlers.py
forloop_modules/function_handlers/control_flow_handlers.py
forloop_modules/function_handlers/dash_handlers.py
forloop_modules/function_handlers/data_handlers.py
forloop_modules/function_handlers/database_handlers.py
forloop_modules/function_handlers/datetime_handlers.py
forloop_modules/function_handlers/file_managment_handlers.py
forloop_modules/function_handlers/input_waiter.py
forloop_modules/function_handlers/integration_handlers.py
forloop_modules/function_handlers/mapping_handlers.py
forloop_modules/function_handlers/model_handlers.py
forloop_modules/function_handlers/orchestration_handlers.py
forloop_modules/function_handlers/rpa_handlers.py
forloop_modules/function_handlers/variable_handlers.py
forloop_modules/function_handlers/webscraping_handlers.py
forloop_modules/function_handlers/auxilliary/__init__.py
forloop_modules/function_handlers/auxilliary/abstract_function_handler.py
forloop_modules/function_handlers/auxilliary/auxiliary_functions.py
forloop_modules/function_handlers/auxilliary/data_types_validation.py
forloop_modules/function_handlers/auxilliary/docs.py
forloop_modules/function_handlers/auxilliary/forloop_code_eval.py
forloop_modules/function_handlers/auxilliary/form_dict_list.py
forloop_modules/function_handlers/auxilliary/node_type_categories_manager.py
forloop_modules/function_handlers/transformations/__init__.py
forloop_modules/function_handlers/transformations/basic_transforms.py
forloop_modules/function_handlers/transformations/imputation.py
forloop_modules-1.6.5.dist-info/LICENSE
forloop_modules-1.6.5.dist-info/METADATA
forloop_modules-1.6.5.dist-info/WHEEL
forloop_modules-1.6.5.dist-info/top_level.txt
forloop_modules-1.6.5.dist-info/RECORD
