Metadata-Version: 2.1
Name: forloop_modules
Version: 1.6.5
Summary: This package contains open source modules and integrations within Forloop.ai platform
Home-page: https://github.com/ForloopAI/forloop_modules
Author: DovaX
Author-email: dovax.ai@gmail.com
Classifier: Programming Language :: Python :: 3
Classifier: License :: OSI Approved :: MIT License
Classifier: Operating System :: OS Independent
Requires-Python: >=3.6
License-File: LICENSE
Requires-Dist: flogg
